{"gameHistory":[{"startDate":"20/04/2023 17:22:30","gameLength":"0:08","gameMode":"Classique","namePlayer1":"Marcy","namePlayer2":"","winnerName":"","nameAbandon":"Marcy"},{"startDate":"20/04/2023 17:23:55","gameLength":"0:07","gameMode":"Temps Limite","namePlayer2":"","winnerName":""},{"startDate":"20/04/2023 17:30:45","gameLength":"0:06","gameMode":"Classique","namePlayer1":"Marcy","namePlayer2":"","winnerName":"","nameAbandon":""},{"startDate":"20/04/2023 17:51:03","gameLength":"0:04","gameMode":"Classique","namePlayer1":"Marcy","namePlayer2":"","winnerName":"","nameAbandon":"Marcy"},{"startDate":"20/04/2023 18:42:51","gameLength":"0:15","gameMode":"Classique","namePlayer2":"","winnerName":""},{"startDate":"20/04/2023 18:43:27","gameLength":"0:08","gameMode":"Temps Limite","namePlayer1":"Marcy","namePlayer2":"","winnerName":"","nameAbandon":"Marcy"},{"startDate":"20/04/2023 18:44:16","gameLength":"0:03","gameMode":"Classique","namePlayer2":"","winnerName":""},{"startDate":"20/04/2023 18:44:25","gameLength":"0:06","gameMode":"Temps Limite","namePlayer1":"Marcy","namePlayer2":"","winnerName":"","nameAbandon":"Marcy"}]}